bosch_mode2_automation/__init__.py
bosch_mode2_automation/bosch_mode2_automation.py
bosch_mode2_automation-0.1.0.dist-info/LICENSE
bosch_mode2_automation-0.1.0.dist-info/METADATA
bosch_mode2_automation-0.1.0.dist-info/WHEEL
bosch_mode2_automation-0.1.0.dist-info/top_level.txt
bosch_mode2_automation-0.1.0.dist-info/RECORD
