Metadata-Version: 2.2
Name: bosch_mode2_automation
Version: 0.1.0
Summary: A library for interacting with Bosch Intrusion Mode 2 panels
Home-page: https://github.com/yourusername/bosch_mode2_automation
Author: Your Name
Author-email: your.email@example.com
Classifier: Programming Language :: Python :: 3
Classifier: License :: OSI Approved :: MIT License
Classifier: Operating System :: OS Independent
Requires-Python: >=3.6
License-File: LICENSE
Dynamic: author
Dynamic: author-email
Dynamic: classifier
Dynamic: description
Dynamic: description-content-type
Dynamic: home-page
Dynamic: requires-python
Dynamic: summary
